Compiled from "Main.java"
class Main {
  Main();
    Code:
       0: aload_0       
       1: invokespecial #1                  // Method java/lang/Object."<init>":()V
       4: return        

  public static void main(java.lang.String[]) throws java.lang.InstantiationException, java.lang.IllegalAccessException;
    Code:
       0: new           #2                  // class Main$S
       3: dup           
       4: invokespecial #3                  // Method Main$S."<init>":()V
       7: astore_1      
       8: aload_1       
       9: new           #4                  // class java/util/ArrayList
      12: dup           
      13: invokespecial #5                  // Method java/util/ArrayList."<init>":()V
      16: invokevirtual #6                  // Method Main$S.handle:(Ljava/util/List;)V
      19: return        

  static <T extends Main$P> T create(java.lang.Class<T>) throws java.lang.InstantiationException, java.lang.IllegalAccessException;
    Code:
       0: aload_0       
       1: invokevirtual #7                  // Method java/lang/Class.newInstance:()Ljava/lang/Object;
       4: checkcast     #8                  // class Main$P
       7: areturn       
}
